fhelwr/__init__.py
fhelwr/client.py
fhelwr/model.py
fhelwr/ext/__init__.py
fhelwr/ext/ner/__init__.py
fhelwr/ext/ner/bert.py
fhelwr/ext/ner/transformer.py
fhelwr/strategy/__init__.py
fhelwr/strategy/fedavg.py
fhelwr-0.1.2.dist-info/LICENSE
fhelwr-0.1.2.dist-info/METADATA
fhelwr-0.1.2.dist-info/WHEEL
fhelwr-0.1.2.dist-info/top_level.txt
fhelwr-0.1.2.dist-info/RECORD
